logparsekit/__init__.py
logparsekit/kits.py
logparsekit-0.1.1.dist-info/METADATA
logparsekit-0.1.1.dist-info/WHEEL
logparsekit-0.1.1.dist-info/licenses/LICENSE
logparsekit-0.1.1.dist-info/RECORD
